{
  "lastChecked": "2026-03-09T09:46:48Z",
  "components": {
    "argocd": {
      "name": "ArgoCD",
      "url": "https://argocd.plateng.dev",
      "status": "up",
      "httpCode": 200,
      "responseMs": 227,
      "lastUp": "2026-03-09T09:46:48Z"
    },
    "backstage": {
      "name": "Backstage",
      "url": "https://backstage.plateng.dev",
      "status": "up",
      "httpCode": 200,
      "responseMs": 251,
      "lastUp": "2026-03-09T09:46:48Z"
    },
    "grafana": {
      "name": "Grafana",
      "url": "https://grafana.plateng.dev",
      "status": "up",
      "httpCode": 302,
      "responseMs": 144,
      "lastUp": "2026-03-09T09:46:48Z"
    },
    "kargo": {
      "name": "Kargo",
      "url": "https://kargo.plateng.dev",
      "status": "up",
      "httpCode": 200,
      "responseMs": 182,
      "lastUp": "2026-03-09T09:46:48Z"
    },
    "dex": {
      "name": "Dex",
      "url": "https://dex.plateng.dev/.well-known/openid-configuration",
      "status": "up",
      "httpCode": 200,
      "responseMs": 250,
      "lastUp": "2026-03-09T09:46:48Z"
    }
  },
  "daily": [
    {
      "date": "2026-03-09",
      "checksTotal": 13,
      "checksUp": 13,
      "uptimePercent": 100
    }
  ]
}
